[
  {
    "smartDeviceID": 102,
    "history": [
      490,
      351,
      272,
      408,
      460,
      397,
      21,
      178,
      295,
      131,
      477,
      297,
      483,
      204,
      426,
      157
    ]
  },
  {
    "smartDeviceID": 103,
    "history": []
  },
  {
    "smartDeviceID": 104,
    "history": []
  },
  {
    "smartDeviceID": 105,
    "history": []
  },
  {
    "smartDeviceID": 108,
    "history": []
  },
  {
    "smartDeviceID": 109,
    "history": []
  },
  {
    "smartDeviceID": 110,
    "history": []
  },
  {
    "smartDeviceID": 113,
    "history": []
  },
  {
    "smartDeviceID": 114,
    "history": []
  },
  {
    "smartDeviceID": 115,
    "history": []
  },
  {
    "smartDeviceID": 116,
    "history": []
  },
  {
    "smartDeviceID": 117,
    "history": []
  },
  {
    "smartDeviceID": 118,
    "history": []
  },
  {
    "smartDeviceID": 119,
    "history": []
  },
  {
    "smartDeviceID": 120,
    "history": []
  },
  {
    "smartDeviceID": 121,
    "history": []
  },
  {
    "smartDeviceID": 122,
    "history": []
  },
  {
    "smartDeviceID": 123,
    "history": []
  },
  {
    "smartDeviceID": 124,
    "history": []
  },
  {
    "smartDeviceID": 119,
    "history": []
  },
  {
    "smartDeviceID": 120,
    "history": []
  },
  {
    "smartDeviceID": 121,
    "history": []
  },
  {
    "smartDeviceID": 124,
    "history": []
  },
  {
    "smartDeviceID": 125,
    "history": []
  },
  {
    "smartDeviceID": 126,
    "history": []
  },
  {
    "smartDeviceID": 127,
    "history": []
  },
  {
    "smartDeviceID": 128,
    "history": []
  },
  {
    "smartDeviceID": 129,
    "history": []
  },
  {
    "smartDeviceID": 130,
    "history": []
  },
  {
    "smartDeviceID": 131,
    "history": []
  },
  {
    "smartDeviceID": 132,
    "history": []
  },
  {
    "smartDeviceID": 135,
    "history": []
  },
  {
    "smartDeviceID": 136,
    "history": []
  },
  {
    "smartDeviceID": 137,
    "history": []
  },
  {
    "smartDeviceID": 140,
    "history": []
  },
  {
    "smartDeviceID": 141,
    "history": []
  },
  {
    "smartDeviceID": 142,
    "history": []
  },
  {
    "smartDeviceID": 146,
    "history": []
  },
  {
    "smartDeviceID": 147,
    "history": []
  },
  {
    "smartDeviceID": 148,
    "history": []
  },
  {
    "smartDeviceID": 151,
    "history": []
  },
  {
    "smartDeviceID": 152,
    "history": []
  },
  {
    "smartDeviceID": 153,
    "history": []
  },
  {
    "smartDeviceID": 156,
    "history": []
  },
  {
    "smartDeviceID": 157,
    "history": []
  },
  {
    "smartDeviceID": 158,
    "history": []
  },
  {
    "smartDeviceID": 161,
    "history": []
  },
  {
    "smartDeviceID": 162,
    "history": []
  },
  {
    "smartDeviceID": 163,
    "history": []
  }
]